DeTrusty/Logger.py
DeTrusty/__init__.py
DeTrusty/__version__.py
DeTrusty/utils.py
DeTrusty/Decomposer/Decomposer.py
DeTrusty/Decomposer/Planner.py
DeTrusty/Decomposer/Tree.py
DeTrusty/Decomposer/__init__.py
DeTrusty/Decomposer/utils.py
DeTrusty/Molecule/MTCreation.py
DeTrusty/Molecule/MTEndpoint.py
DeTrusty/Molecule/MTManager.py
DeTrusty/Molecule/__init__.py
DeTrusty/Operators/Join.py
DeTrusty/Operators/Optional.py
DeTrusty/Operators/Union.py
DeTrusty/Operators/__init__.py
DeTrusty/Operators/AnapsidOperators/OperatorStructures.py
DeTrusty/Operators/AnapsidOperators/Xbind.py
DeTrusty/Operators/AnapsidOperators/Xdistinct.py
DeTrusty/Operators/AnapsidOperators/Xexpression.py
DeTrusty/Operators/AnapsidOperators/Xfilter.py
DeTrusty/Operators/AnapsidOperators/Xgjoin.py
DeTrusty/Operators/AnapsidOperators/Xgoptional.py
DeTrusty/Operators/AnapsidOperators/Xgroupby.py
DeTrusty/Operators/AnapsidOperators/Xhaving.py
DeTrusty/Operators/AnapsidOperators/Xlimit.py
DeTrusty/Operators/AnapsidOperators/Xnjoin.py
DeTrusty/Operators/AnapsidOperators/Xnoptional.py
DeTrusty/Operators/AnapsidOperators/Xoffset.py
DeTrusty/Operators/AnapsidOperators/Xorderby.py
DeTrusty/Operators/AnapsidOperators/Xproject.py
DeTrusty/Operators/AnapsidOperators/Xunion.py
DeTrusty/Operators/AnapsidOperators/Xvalues.py
DeTrusty/Operators/AnapsidOperators/__init__.py
DeTrusty/Operators/BlockingOperators/HashJoin.py
DeTrusty/Operators/BlockingOperators/HashOptional.py
DeTrusty/Operators/BlockingOperators/NestedLoopJoin.py
DeTrusty/Operators/BlockingOperators/NestedLoopOptional.py
DeTrusty/Operators/BlockingOperators/OperatorStructures.py
DeTrusty/Operators/BlockingOperators/Union.py
DeTrusty/Operators/BlockingOperators/__init__.py
DeTrusty/Operators/NonBlockingOperators/NestedHashJoinFilter.py
DeTrusty/Operators/NonBlockingOperators/NestedHashJoinValues.py
DeTrusty/Operators/NonBlockingOperators/NestedHashOptionalFilter.py
DeTrusty/Operators/NonBlockingOperators/NestedHashOptionalValues.py
detrusty-0.22.0.dist-info/licenses/LICENSE
detrusty-0.22.0.dist-info/METADATA
detrusty-0.22.0.dist-info/WHEEL
detrusty-0.22.0.dist-info/top_level.txt
detrusty-0.22.0.dist-info/RECORD
