Metadata-Version: 2.4
Name: DeTrusty
Version: 0.22.0
Summary: DeTrusty - Decentralized and Trustable Query Engine
Home-page: https://github.com/SDM-TIB/DeTrusty
Download-URL: https://github.com/SDM-TIB/DeTrusty/archive/refs/tags/v0.22.0.tar.gz
Author: Philipp D. Rohde
Author-email: philipp.rohde@tib.eu
License: GNU/GPLv3
Project-URL: Documentation, https://sdm-tib.github.io/DeTrusty/
Project-URL: Changes, https://sdm-tib.github.io/DeTrusty/changelog.html
Project-URL: Source Code, https://github.com/SDM-TIB/DeTrusty
Project-URL: Issue Tracker, https://github.com/SDM-TIB/DeTrusty/issues
Classifier: Development Status :: 4 - Beta
Classifier: Programming Language :: Python
Classifier: Programming Language :: Python :: 3
Classifier: Programming Language :: Python :: 3 :: Only
Classifier: Programming Language :: Python :: 3.9
Classifier: Programming Language :: Python :: 3.10
Classifier: Programming Language :: Python :: 3.11
Classifier: Programming Language :: Python :: 3.12
Classifier: Programming Language :: Python :: 3.13
Classifier: License :: OSI Approved :: GNU General Public License v3 (GPLv3)
Classifier: Operating System :: OS Independent
Classifier: Intended Audience :: Science/Research
Requires-Python: >=3.8
License-File: LICENSE
Requires-Dist: requests>=2.32.0
Requires-Dist: ply==3.11
Requires-Dist: rdflib>=6.0.0
Requires-Dist: python-dateutil>=2.8.0
Requires-Dist: pyoxigraph>=0.4.0
Dynamic: author
Dynamic: author-email
Dynamic: classifier
Dynamic: description
Dynamic: description-content-type
Dynamic: download-url
Dynamic: home-page
Dynamic: license
Dynamic: license-file
Dynamic: project-url
Dynamic: requires-dist
Dynamic: requires-python
Dynamic: summary
